Metadata-Version: 1.1
Name: pdext
Version: 0.0.1
Summary: Pandas Extention python module
Home-page: https://github.com/malneni/PdExt
Author: Venkatesh Malneni
Author-email: malneni258@gmail.com
License: MIT
Download-URL: https://github.com/malneni/PdExt/archive/V_001.tar.gz
Keywords: pandas,Split Columns,Multiple Rows
Platform: UNKNOWN
Classifier: Development Status :: 3 - Alpha
Classifier: Intended Audience :: Developers
Classifier: License :: OSI Approved :: MIT License
Classifier: Programming Language :: Python :: 3.7
